tap_annie/__init__.py
tap_annie/api_annie.py
tap_annie/checker.py
tap_annie/schemas/app_ratings.json
tap_annie/schemas/product_sales.json
tap_annie/schemas/product_store_metrics.json
tap_annie-0.1.6.dist-info/LICENSE
tap_annie-0.1.6.dist-info/METADATA
tap_annie-0.1.6.dist-info/WHEEL
tap_annie-0.1.6.dist-info/entry_points.txt
tap_annie-0.1.6.dist-info/top_level.txt
tap_annie-0.1.6.dist-info/RECORD
