Metadata-Version: 2.1
Name: tap-annie
Version: 0.1.6
Summary: Singer.io tap for extracting data
Home-page: http://singer.io
Author: Stitch
Author-email: UNKNOWN
License: UNKNOWN
Platform: UNKNOWN
Classifier: Programming Language :: Python :: 3 :: Only
Requires-Dist: singer-python (>=5.0.12)
Requires-Dist: requests
Requires-Dist: google-auth
Requires-Dist: google-cloud
Requires-Dist: google-cloud-bigquery
